LICENSE
README.md
pydngconverter/__init__.py
pydngconverter/compat.py
pydngconverter/dngconverter.py
pydngconverter/flags.py
pydngconverter/main.py
pydngconverter/utils.py
pydngconverter-0.3.0.dist-info/LICENSE
pydngconverter-0.3.0.dist-info/METADATA
pydngconverter-0.3.0.dist-info/WHEEL
pydngconverter-0.3.0.dist-info/RECORD
