Metadata-Version: 2.1
Name: pydngconverter
Version: 0.3.0
Summary: Python Interface for the Adobe's DNG Converter
Home-page: https://github.com/BradenM/pydngconverter
License: MIT
Keywords: pydng,dng,dngconverter,raw,api
Author: Braden Mars
Author-email: bradenmars@bradenmars.me
Requires-Python: >=3.8,<4.0
Classifier: Intended Audience :: Developers
Classifier: Intended Audience :: Other Audience
Classifier: License :: OSI Approved :: MIT License
Classifier: Programming Language :: Python :: 3
Classifier: Programming Language :: Python :: 3.8
Classifier: Programming Language :: Python :: 3.9
Classifier: Programming Language :: Python :: 3.10
Classifier: Programming Language :: Python :: 3.11
Classifier: Programming Language :: Python :: 3
Classifier: Programming Language :: Python :: 3.10
Classifier: Programming Language :: Python :: 3.11
Classifier: Programming Language :: Python :: 3.8
Classifier: Programming Language :: Python :: 3.9
Classifier: Programming Language :: Python :: Implementation :: CPython
Classifier: Topic :: Scientific/Engineering :: Image Processing
Requires-Dist: Wand (>=0.6,<0.7)
Requires-Dist: psutil (>=5.9,<5.10)
Requires-Dist: rich (>=13.3.1,<14.0.0)
Requires-Dist: typing-extensions (>=4.5.0,<5.0.0)
Project-URL: Documentation, https://bradenm.github.io/pydngconverter
Project-URL: Repository, https://github.com/BradenM/pydngconverter
